Metadata-Version: 1.0
Name: pdistributions
Version: 0.1
Summary: Gaussian distributions1
Home-page: UNKNOWN
Author: Muhammad Liman Dahiru
Author-email: mlimand76@gmail.com
License: UNKNOWN
Platform: UNKNOWN
